layerview/__init__.py
layerview/app/__init__.py
layerview/app/app.py
layerview/app/constants.py
layerview/app/dialog_info/__init__.py
layerview/app/dialog_info/dialog.py
layerview/app/dialog_info/res/md/about.md
layerview/app/dialog_info/res/md/img/axis_colors.png
layerview/app/dialog_info/res/md/img/build_area.png
layerview/app/dialog_info/res/md/img/camera_mode.png
layerview/app/dialog_info/res/md/img/clear.png
layerview/app/dialog_info/res/md/img/coloring_mode.png
layerview/app/dialog_info/res/md/img/drag_n_drop.png
layerview/app/dialog_info/res/md/img/file_open.png
layerview/app/dialog_info/res/md/img/layer_info.png
layerview/app/dialog_info/res/md/img/model_info.png
layerview/app/dialog_info/res/md/img/visible_layers.png
layerview/app/dialog_info/res/md/img/visible_range.png
layerview/app/dialog_info/res/md/manual.md
layerview/app/dialog_load/__init__.py
layerview/app/dialog_load/dialog.py
layerview/app/dialog_load/worker.py
layerview/app/main_window/__init__.py
layerview/app/main_window/controller.py
layerview/app/main_window/dto.py
layerview/app/main_window/errors.py
layerview/app/main_window/model.py
layerview/app/main_window/view.py
layerview/app/main_window/visualization.py
layerview/app/pyuic/.gitignore
layerview/app/pyuic/__init__.py
layerview/app/pyuic/dialog_info.py
layerview/app/pyuic/dialog_load.py
layerview/app/pyuic/main_window.py
layerview/cli.py
layerview/common/__init__.py
layerview/common/markdown.py
layerview/common/mixins.py
layerview/gcode/__init__.py
layerview/gcode/commands.py
layerview/gcode/gcode.py
layerview/gcode/lexemes.py
layerview/gcode/parser.py
layerview/gcode/tokens.py
layerview/gcode/utils.py
layerview/simulation/__init__.py
layerview/simulation/machine.py
layerview/visualization/__init__.py
layerview/visualization/linalg.py
layerview/visualization/nodes/__init__.py
layerview/visualization/nodes/assets/textures/layerview.png
layerview/visualization/nodes/build_area.py
layerview/visualization/nodes/builder.py
layerview-0.1.6.dist-info/entry_points.txt
layerview-0.1.6.dist-info/LICENSE
layerview-0.1.6.dist-info/WHEEL
layerview-0.1.6.dist-info/METADATA
layerview-0.1.6.dist-info/RECORD
