Metadata-Version: 2.1
Name: layerview
Version: 0.1.6
Summary: LayerView is a G-code visualizer and inspector.
Home-page: https://github.com/majabojarska/LayerView
License: GPL-3.0-only
Author: Maja Bojarska
Author-email: majabojarska98@gmail.com
Requires-Python: >=3.8,<3.10
Classifier: Development Status :: 2 - Pre-Alpha
Classifier: Intended Audience :: Developers
Classifier: License :: OSI Approved :: GNU General Public License v3 (GPLv3)
Classifier: Natural Language :: English
Classifier: Operating System :: MacOS
Classifier: Operating System :: Microsoft :: Windows :: Windows 10
Classifier: Operating System :: POSIX :: Linux
Classifier: Programming Language :: Python :: 3
Classifier: Programming Language :: Python :: 3.8
Classifier: Programming Language :: Python :: 3.9
Classifier: Programming Language :: Python :: Implementation :: CPython
Classifier: Topic :: Multimedia :: Graphics :: 3D Rendering
Classifier: Topic :: Printing
Requires-Dist: Panda3D (==1.10.7)
Requires-Dist: Pillow (>=8.0.1,<9.0.0)
Requires-Dist: PyQt5 (>=5.15.2,<6.0.0)
Requires-Dist: QPanda3D (==0.2.8)
Requires-Dist: numpy (>=1.22.4,<2.0.0)
